README.rst
setup.py
rskpp/__init__.py
rskpp/example.py
rskpp/rskpp.py
rskpp.egg-info/PKG-INFO
rskpp.egg-info/SOURCES.txt
rskpp.egg-info/dependency_links.txt
rskpp.egg-info/not-zip-safe
rskpp.egg-info/requires.txt
rskpp.egg-info/top_level.txt